README.rst
setup.cfg
setup.py
django_pg_partitioning.egg-info/PKG-INFO
django_pg_partitioning.egg-info/SOURCES.txt
django_pg_partitioning.egg-info/dependency_links.txt
django_pg_partitioning.egg-info/requires.txt
django_pg_partitioning.egg-info/top_level.txt
pg_partitioning/__init__.py
pg_partitioning/apps.py
pg_partitioning/constants.py
pg_partitioning/decorators.py
pg_partitioning/manager.py
pg_partitioning/models.py
pg_partitioning/shortcuts.py
pg_partitioning/signals.py
pg_partitioning/migrations/0001_initial.py
pg_partitioning/migrations/__init__.py
pg_partitioning/patch/__init__.py
pg_partitioning/patch/schema.py