Metadata-Version: 2.1
Name: django-pg-partitioning
Version: 0.11
Summary: A Django extension that supports PostgreSQL 11 time ranges and list partitioning.
Home-page: https://github.com/chaitin/django-pg-partitioning
Author: Boyce Li
Author-email: monobiao@gmail.com
License: UNKNOWN
Platform: UNKNOWN
Classifier: Development Status :: 4 - Beta
Classifier: Programming Language :: Python :: 3.6
Classifier: Programming Language :: Python :: 3.7
Classifier: Framework :: Django :: 2.0
Classifier: Framework :: Django :: 2.1
Classifier: License :: OSI Approved :: MIT License
Classifier: Operating System :: OS Independent
Classifier: Topic :: Software Development :: Libraries :: Python Modules
Requires-Python: >=3.6
Provides-Extra: dev
Provides-Extra: all
Provides-Extra: django
